{"assetProfile": {"address1": "1090 King Georges Post Road", "address2": "Suite 603", "city": "Edison", "state": "NJ", "zip": "08837", "country": "United States", "phone": "732 661 9641", "website": "https://www.strikeforcetech.com", "industry": "Software\u2014Infrastructure", "sector": "Technology", "longBusinessSummary": "StrikeForce Technologies, Inc. provides software development and services worldwide. The company develops and licenses various identification protection software products to protect computer networks from unauthorized access, as well as to protect network owners and users from cyber security attacks and data breaches. It offers ProtectID, an authentication platform to authenticate computer network users by various methods, including traditional passwords combined with a telephone, iPhone, Droid, Blackberry, PDA, multiple computer secure sessions, biometric identification, and encrypted devices, as well as through a push authentication method; and GuardedID that prevents the use of spyware/malware to collect user information. The company's products also comprise MobileTrust, an iPhone/iPad and Android device password vault that includes a password generator, as well as provides for mobile multi-factor one time password authentication; GuardedID mobile software development kit; SafeVchat video conferencing product; and PrivacyLok, which offers protective mechanisms. In addition, it provides software and hardware that are contractually licensed from other vendors, such as tokens, as well as additional authentication and telecommunication software devices. The company markets its products to financial service firms; healthcare related, legal services, virtual private network, technology service, and e-commerce companies; automotive; government agencies; multi-level marketing groups; and retail distributors, as well as the enterprise market in general. It sells its products directly to consumers through internet, distributors, resellers, third party agents, affiliates, and original equipment manufacturer agreements. The company was formerly known as StrikeForce Technical Services Corporation and changed its name to StrikeForce Technologies, Inc. in September 2004. StrikeForce Technologies, Inc. was incorporated in 2001 and is headquartered in Edison, New Jersey.", "fullTimeEmployees": 11, "companyOfficers": [{"maxAge": 1, "name": "Mr. Mark L. Kay", "age": 72, "title": "CEO & Chairman", "yearBorn": 1949, "fiscalYear": 2020, "totalPay": {"raw": 164000, "fmt": "164k", "longFmt": "164,000"}, "exercisedValue": {"raw": 0, "fmt": null, "longFmt": "0"}, "unexercisedValue": {"raw": 44984, "fmt": "44.98k", "longFmt": "44,984"}}, {"maxAge": 1, "name": "Mr. Ramarao  Pemmaraju", "age": 60, "title": "Co-Founder, CTO, Sec. & Director", "yearBorn": 1961, "fiscalYear": 2020, "totalPay": {"raw": 167000, "fmt": "167k", "longFmt": "167,000"}, "exercisedValue": {"raw": 0, "fmt": null, "longFmt": "0"}, "unexercisedValue": {"raw": 44984, "fmt": "44.98k", "longFmt": "44,984"}}, {"maxAge": 1, "name": "Mr. George  Waller", "age": 63, "title": "Co-Founder, Exec. VP, Head of Marketing & Director", "yearBorn": 1958, "fiscalYear": 2020, "totalPay": {"raw": 166000, "fmt": "166k", "longFmt": "166,000"}, "exercisedValue": {"raw": 0, "fmt": null, "longFmt": "0"}, "unexercisedValue": {"raw": 44984, "fmt": "44.98k", "longFmt": "44,984"}}, {"maxAge": 1, "name": "Mr. Philip E. Blocker", "age": 64, "title": "Chief Financial Officer", "yearBorn": 1957, "exercisedValue": {"raw": 0, "fmt": null, "longFmt": "0"}, "unexercisedValue": {"raw": 0, "fmt": null, "longFmt": "0"}}, {"maxAge": 1, "name": "Brian  Hart", "title": "Mang. of Sales", "exercisedValue": {"raw": 0, "fmt": null, "longFmt": "0"}, "unexercisedValue": {"raw": 0, "fmt": null, "longFmt": "0"}}], "compensationAsOfEpochDate": 1609372800, "maxAge": 86400}, "recommendationTrend": {"trend": [{"period": "0m", "strongBuy": 0, "buy": 0, "hold": 0, "sell": 0, "strongSell": 0}, {"period": "-1m", "strongBuy": 0, "buy": 0, "hold": 0, "sell": 0, "strongSell": 0}, {"period": "-2m", "strongBuy": 0, "buy": 0, "hold": 0, "sell": 0, "strongSell": 0}, {"period": "-3m", "strongBuy": 0, "buy": 0, "hold": 0, "sell": 0, "strongSell": 0}], "maxAge": 86400}, "cashflowStatementHistory": {"cashflowStatements": [{"maxAge": 1, "endDate": {"raw": 1609372800, "fmt": "2020-12-31"}, "netIncome": {"raw": -10043000, "fmt": "-10.04M", "longFmt": "-10,043,000"}, "depreciation": {"raw": 56000, "fmt": "56k", "longFmt": "56,000"}, "changeToNetincome": {"raw": 6704000, "fmt": "6.7M", "longFmt": "6,704,000"}, "changeToLiabilities": {"raw": -77000, "fmt": "-77k", "longFmt": "-77,000"}, "changeToOperatingActivities": {"raw": 499000, "fmt": "499k", "longFmt": "499,000"}, "totalCashFromOperatingActivities": {"raw": -2256000, "fmt": "-2.26M", "longFmt": "-2,256,000"}, "capitalExpenditures": {"raw": -1000, "fmt": "-1k", "longFmt": "-1,000"}, "totalCashflowsFromInvestingActivities": {"raw": -1000, "fmt": "-1k", "longFmt": "-1,000"}, "netBorrowings": {"raw": 1368000, "fmt": "1.37M", "longFmt": "1,368,000"}, "totalCashFromFinancingActivities": {"raw": 2344000, "fmt": "2.34M", "longFmt": "2,344,000"}, "changeInCash": {"raw": 87000, "fmt": "87k", "longFmt": "87,000"}, "issuanceOfStock": {"raw": 976000, "fmt": "976k", "longFmt": "976,000"}}, {"maxAge": 1, "endDate": {"raw": 1577750400, "fmt": "2019-12-31"}, "netIncome": {"raw": -3528000, "fmt": "-3.53M", "longFmt": "-3,528,000"}, "depreciation": {"raw": 54000, "fmt": "54k", "longFmt": "54,000"}, "changeToNetincome": {"raw": 425000, "fmt": "425k", "longFmt": "425,000"}, "changeToAccountReceivables": {"raw": 1000, "fmt": "1k", "longFmt": "1,000"}, "changeToLiabilities": {"raw": 170000, "fmt": "170k", "longFmt": "170,000"}, "changeToOperatingActivities": {"raw": 446000, "fmt": "446k", "longFmt": "446,000"}, "totalCashFromOperatingActivities": {"raw": -1385000, "fmt": "-1.39M", "longFmt": "-1,385,000"}, "capitalExpenditures": {"raw": -1000, "fmt": "-1k", "longFmt": "-1,000"}, "totalCashflowsFromInvestingActivities": {"raw": -1000, "fmt": "-1k", "longFmt": "-1,000"}, "netBorrowings": {"raw": 1375000, "fmt": "1.38M", "longFmt": "1,375,000"}, "totalCashFromFinancingActivities": {"raw": 1375000, "fmt": "1.38M", "longFmt": "1,375,000"}, "changeInCash": {"raw": -11000, "fmt": "-11k", "longFmt": "-11,000"}, "issuanceOfStock": {"raw": 976000, "fmt": "976k", "longFmt": "976,000"}}, {"maxAge": 1, "endDate": {"raw": 1546214400, "fmt": "2018-12-31"}, "netIncome": {"raw": -3281509, "fmt": "-3.28M", "longFmt": "-3,281,509"}, "depreciation": {"raw": 6750, "fmt": "6.75k", "longFmt": "6,750"}, "changeToNetincome": {"raw": -79825, "fmt": "-79.83k", "longFmt": "-79,825"}, "changeToAccountReceivables": {"raw": 26805, "fmt": "26.8k", "longFmt": "26,805"}, "changeToLiabilities": {"raw": -11771, "fmt": "-11.77k", "longFmt": "-11,771"}, "changeToOperatingActivities": {"raw": 442672, "fmt": "442.67k", "longFmt": "442,672"}, "totalCashFromOperatingActivities": {"raw": -2023545, "fmt": "-2.02M", "longFmt": "-2,023,545"}, "capitalExpenditures": {"raw": -6279, "fmt": "-6.28k", "longFmt": "-6,279"}, "totalCashflowsFromInvestingActivities": {"raw": -6279, "fmt": "-6.28k", "longFmt": "-6,279"}, "netBorrowings": {"raw": 1660500, "fmt": "1.66M", "longFmt": "1,660,500"}, "totalCashFromFinancingActivities": {"raw": 1660500, "fmt": "1.66M", "longFmt": "1,660,500"}, "changeInCash": {"raw": -369324, "fmt": "-369.32k", "longFmt": "-369,324"}, "issuanceOfStock": {"raw": 976000, "fmt": "976k", "longFmt": "976,000"}}, {"maxAge": 1, "endDate": {"raw": 1514678400, "fmt": "2017-12-31"}, "netIncome": {"raw": -3206500, "fmt": "-3.21M", "longFmt": "-3,206,500"}, "depreciation": {"raw": 6618, "fmt": "6.62k", "longFmt": "6,618"}, "changeToNetincome": {"raw": 672102, "fmt": "672.1k", "longFmt": "672,102"}, "changeToAccountReceivables": {"raw": 104555, "fmt": "104.56k", "longFmt": "104,555"}, "changeToLiabilities": {"raw": 46553, "fmt": "46.55k", "longFmt": "46,553"}, "changeToOperatingActivities": {"raw": 285340, "fmt": "285.34k", "longFmt": "285,340"}, "totalCashFromOperatingActivities": {"raw": -1716332, "fmt": "-1.72M", "longFmt": "-1,716,332"}, "capitalExpenditures": {"raw": -3314, "fmt": "-3.31k", "longFmt": "-3,314"}, "totalCashflowsFromInvestingActivities": {"raw": -3314, "fmt": "-3.31k", "longFmt": "-3,314"}, "netBorrowings": {"raw": -209000, "fmt": "-209k", "longFmt": "-209,000"}, "otherCashflowsFromFinancingActivities": {"raw": 1500000, "fmt": "1.5M", "longFmt": "1,500,000"}, "totalCashFromFinancingActivities": {"raw": 1371000, "fmt": "1.37M", "longFmt": "1,371,000"}, "changeInCash": {"raw": -348646, "fmt": "-348.65k", "longFmt": "-348,646"}, "issuanceOfStock": {"raw": 976000, "fmt": "976k", "longFmt": "976,000"}}], "maxAge": 86400}, "indexTrend": {"maxAge": 1, "symbol": "SP5", "peRatio": {"raw": 13.0519, "fmt": "13.05"}, "pegRatio": {"raw": 2.71054, "fmt": "2.71"}, "estimates": [{"period": "0q", "growth": {"raw": 0.253, "fmt": "0.25"}}, {"period": "+1q", "growth": {"raw": 0.22399999, "fmt": "0.22"}}, {"period": "0y", "growth": {"raw": 0.45900002, "fmt": "0.46"}}, {"period": "+1y", "growth": {"raw": 0.054, "fmt": "0.05"}}, {"period": "+5y", "growth": {"raw": 0.13400501, "fmt": "0.13"}}, {"period": "-5y", "growth": {}}]}, "defaultKeyStatistics": {"maxAge": 1, "priceHint": {"raw": 4, "fmt": "4", "longFmt": "4"}, "enterpriseValue": {"raw": 46877356, "fmt": "46.88M", "longFmt": "46,877,356"}, "forwardPE": {}, "profitMargins": {"raw": 0.0, "fmt": "0.00%"}, "floatShares": {"raw": 900367210, "fmt": "900.37M", "longFmt": "900,367,210"}, "sharesOutstanding": {"raw": 952921024, "fmt": "952.92M", "longFmt": "952,921,024"}, "sharesShort": {}, "sharesShortPriorMonth": {}, "sharesShortPreviousMonthDate": {}, "dateShortInterest": {}, "sharesPercentSharesOut": {}, "heldPercentInsiders": {"raw": 0.08632, "fmt": "8.63%"}, "heldPercentInstitutions": {"raw": 0.0, "fmt": "0.00%"}, "shortRatio": {}, "shortPercentOfFloat": {}, "beta": {"raw": 3.506397, "fmt": "3.51"}, "morningStarOverallRating": {}, "morningStarRiskRating": {}, "category": null, "bookValue": {"raw": -0.011, "fmt": "-0.01"}, "priceToBook": {}, "annualReportExpenseRatio": {}, "ytdReturn": {}, "beta3Year": {}, "totalAssets": {}, "yield": {}, "fundFamily": null, "fundInceptionDate": {}, "legalType": null, "threeYearAverageReturn": {}, "fiveYearAverageReturn": {}, "priceToSalesTrailing12Months": {}, "lastFiscalYearEnd": {"raw": 1609372800, "fmt": "2020-12-31"}, "nextFiscalYearEnd": {"raw": 1672444800, "fmt": "2022-12-31"}, "mostRecentQuarter": {"raw": 1632960000, "fmt": "2021-09-30"}, "earningsQuarterlyGrowth": {}, "revenueQuarterlyGrowth": {}, "netIncomeToCommon": {"raw": -22936000, "fmt": "-22.94M", "longFmt": "-22,936,000"}, "trailingEps": {"raw": -0.033, "fmt": "-0.0330"}, "forwardEps": {}, "pegRatio": {}, "lastSplitFactor": "1:500", "lastSplitDate": {"raw": 1593043200, "fmt": "2020-06-25"}, "enterpriseToRevenue": {"raw": 236.754, "fmt": "236.75"}, "enterpriseToEbitda": {"raw": -5.017, "fmt": "-5.02"}, "52WeekChange": {}, "SandP52WeekChange": {}, "lastDividendValue": {}, "lastCapGain": {}, "annualHoldingsTurnover": {}}, "industryTrend": {"maxAge": 1, "symbol": null, "peRatio": {}, "pegRatio": {}, "estimates": []}, "quoteType": {"exchange": "PNK", "quoteType": "EQUITY", "symbol": "SFOR", "underlyingSymbol": "SFOR", "shortName": "STRIKEFORCE TECHNOLOGIES INC", "longName": "StrikeForce Technologies, Inc.", "firstTradeDateEpochUtc": 1135002600, "timeZoneFullName": "America/New_York", "timeZoneShortName": "EDT", "uuid": "51b776ad-4287-3a52-aded-b824d10b3705", "gmtOffSetMilliseconds": -14400000, "maxAge": 1}, "incomeStatementHistory": {"incomeStatementHistory": [{"maxAge": 1, "endDate": {"raw": 1609372800, "fmt": "2020-12-31"}, "totalRevenue": {"raw": 207000, "fmt": "207k", "longFmt": "207,000"}, "costOfRevenue": {"raw": 13000, "fmt": "13k", "longFmt": "13,000"}, "grossProfit": {"raw": 194000, "fmt": "194k", "longFmt": "194,000"}, "researchDevelopment": {"raw": 520000, "fmt": "520k", "longFmt": "520,000"}, "sellingGeneralAdministrative": {"raw": 2350000, "fmt": "2.35M", "longFmt": "2,350,000"}, "nonRecurring": {}, "otherOperatingExpenses": {}, "totalOperatingExpenses": {"raw": 2883000, "fmt": "2.88M", "longFmt": "2,883,000"}, "operatingIncome": {"raw": -2676000, "fmt": "-2.68M", "longFmt": "-2,676,000"}, "totalOtherIncomeExpenseNet": {"raw": -7412000, "fmt": "-7.41M", "longFmt": "-7,412,000"}, "ebit": {"raw": -2676000, "fmt": "-2.68M", "longFmt": "-2,676,000"}, "interestExpense": {"raw": -1259000, "fmt": "-1.26M", "longFmt": "-1,259,000"}, "incomeBeforeTax": {"raw": -10088000, "fmt": "-10.09M", "longFmt": "-10,088,000"}, "incomeTaxExpense": {"raw": 0, "fmt": null, "longFmt": "0"}, "minorityInterest": {"raw": -823000, "fmt": "-823k", "longFmt": "-823,000"}, "netIncomeFromContinuingOps": {"raw": -10088000, "fmt": "-10.09M", "longFmt": "-10,088,000"}, "discontinuedOperations": {}, "extraordinaryItems": {}, "effectOfAccountingCharges": {}, "otherItems": {}, "netIncome": {"raw": -10043000, "fmt": "-10.04M", "longFmt": "-10,043,000"}, "netIncomeApplicableToCommonShares": {"raw": -10043000, "fmt": "-10.04M", "longFmt": "-10,043,000"}}, {"maxAge": 1, "endDate": {"raw": 1577750400, "fmt": "2019-12-31"}, "totalRevenue": {"raw": 768000, "fmt": "768k", "longFmt": "768,000"}, "costOfRevenue": {"raw": 10000, "fmt": "10k", "longFmt": "10,000"}, "grossProfit": {"raw": 758000, "fmt": "758k", "longFmt": "758,000"}, "researchDevelopment": {"raw": 520000, "fmt": "520k", "longFmt": "520,000"}, "sellingGeneralAdministrative": {"raw": 1839000, "fmt": "1.84M", "longFmt": "1,839,000"}, "nonRecurring": {}, "otherOperatingExpenses": {}, "totalOperatingExpenses": {"raw": 2369000, "fmt": "2.37M", "longFmt": "2,369,000"}, "operatingIncome": {"raw": -1601000, "fmt": "-1.6M", "longFmt": "-1,601,000"}, "totalOtherIncomeExpenseNet": {"raw": -2147000, "fmt": "-2.15M", "longFmt": "-2,147,000"}, "ebit": {"raw": -1601000, "fmt": "-1.6M", "longFmt": "-1,601,000"}, "interestExpense": {"raw": -1552000, "fmt": "-1.55M", "longFmt": "-1,552,000"}, "incomeBeforeTax": {"raw": -3748000, "fmt": "-3.75M", "longFmt": "-3,748,000"}, "incomeTaxExpense": {"raw": 2000, "fmt": "2k", "longFmt": "2,000"}, "minorityInterest": {"raw": -778000, "fmt": "-778k", "longFmt": "-778,000"}, "netIncomeFromContinuingOps": {"raw": -3750000, "fmt": "-3.75M", "longFmt": "-3,750,000"}, "discontinuedOperations": {}, "extraordinaryItems": {}, "effectOfAccountingCharges": {}, "otherItems": {}, "netIncome": {"raw": -3528000, "fmt": "-3.53M", "longFmt": "-3,528,000"}, "netIncomeApplicableToCommonShares": {"raw": -3528000, "fmt": "-3.53M", "longFmt": "-3,528,000"}}, {"maxAge": 1, "endDate": {"raw": 1546214400, "fmt": "2018-12-31"}, "totalRevenue": {"raw": 233878, "fmt": "233.88k", "longFmt": "233,878"}, "costOfRevenue": {"raw": 14086, "fmt": "14.09k", "longFmt": "14,086"}, "grossProfit": {"raw": 219792, "fmt": "219.79k", "longFmt": "219,792"}, "researchDevelopment": {"raw": 511327, "fmt": "511.33k", "longFmt": "511,327"}, "sellingGeneralAdministrative": {"raw": 2109100, "fmt": "2.11M", "longFmt": "2,109,100"}, "nonRecurring": {}, "otherOperatingExpenses": {}, "totalOperatingExpenses": {"raw": 2634513, "fmt": "2.63M", "longFmt": "2,634,513"}, "operatingIncome": {"raw": -2400635, "fmt": "-2.4M", "longFmt": "-2,400,635"}, "totalOtherIncomeExpenseNet": {"raw": -1435114, "fmt": "-1.44M", "longFmt": "-1,435,114"}, "ebit": {"raw": -2400635, "fmt": "-2.4M", "longFmt": "-2,400,635"}, "interestExpense": {"raw": -1317012, "fmt": "-1.32M", "longFmt": "-1,317,012"}, "incomeBeforeTax": {"raw": -3835749, "fmt": "-3.84M", "longFmt": "-3,835,749"}, "incomeTaxExpense": {"raw": 1500, "fmt": "1.5k", "longFmt": "1,500"}, "minorityInterest": {"raw": -555740, "fmt": "-555.74k", "longFmt": "-555,740"}, "netIncomeFromContinuingOps": {"raw": -3837249, "fmt": "-3.84M", "longFmt": "-3,837,249"}, "discontinuedOperations": {}, "extraordinaryItems": {}, "effectOfAccountingCharges": {}, "otherItems": {}, "netIncome": {"raw": -3281509, "fmt": "-3.28M", "longFmt": "-3,281,509"}, "netIncomeApplicableToCommonShares": {"raw": -3281509, "fmt": "-3.28M", "longFmt": "-3,281,509"}}, {"maxAge": 1, "endDate": {"raw": 1514678400, "fmt": "2017-12-31"}, "totalRevenue": {"raw": 274137, "fmt": "274.14k", "longFmt": "274,137"}, "costOfRevenue": {"raw": 12504, "fmt": "12.5k", "longFmt": "12,504"}, "grossProfit": {"raw": 261633, "fmt": "261.63k", "longFmt": "261,633"}, "researchDevelopment": {"raw": 537282, "fmt": "537.28k", "longFmt": "537,282"}, "sellingGeneralAdministrative": {"raw": 2118054, "fmt": "2.12M", "longFmt": "2,118,054"}, "nonRecurring": {}, "otherOperatingExpenses": {}, "totalOperatingExpenses": {"raw": 2667840, "fmt": "2.67M", "longFmt": "2,667,840"}, "operatingIncome": {"raw": -2393703, "fmt": "-2.39M", "longFmt": "-2,393,703"}, "totalOtherIncomeExpenseNet": {"raw": -741104, "fmt": "-741.1k", "longFmt": "-741,104"}, "ebit": {"raw": -2393703, "fmt": "-2.39M", "longFmt": "-2,393,703"}, "interestExpense": {"raw": -841925, "fmt": "-841.92k", "longFmt": "-841,925"}, "incomeBeforeTax": {"raw": -3134807, "fmt": "-3.13M", "longFmt": "-3,134,807"}, "incomeTaxExpense": {"raw": 71693, "fmt": "71.69k", "longFmt": "71,693"}, "minorityInterest": {"raw": -555740, "fmt": "-555.74k", "longFmt": "-555,740"}, "netIncomeFromContinuingOps": {"raw": -3206500, "fmt": "-3.21M", "longFmt": "-3,206,500"}, "discontinuedOperations": {}, "extraordinaryItems": {}, "effectOfAccountingCharges": {}, "otherItems": {}, "netIncome": {"raw": -3206500, "fmt": "-3.21M", "longFmt": "-3,206,500"}, "netIncomeApplicableToCommonShares": {"raw": -3224278, "fmt": "-3.22M", "longFmt": "-3,224,278"}}], "maxAge": 86400}, "fundOwnership": {"ownershipList": [], "maxAge": 1}, "summaryDetail": {"maxAge": 1, "priceHint": {"raw": 4, "fmt": "4", "longFmt": "4"}, "previousClose": {"raw": 0.02826, "fmt": "0.0283"}, "open": {"raw": 0.0279, "fmt": "0.0279"}, "dayLow": {"raw": 0.02765, "fmt": "0.0277"}, "dayHigh": {"raw": 0.03, "fmt": "0.0300"}, "regularMarketPreviousClose": {"raw": 0.02826, "fmt": "0.0283"}, "regularMarketOpen": {"raw": 0.0279, "fmt": "0.0279"}, "regularMarketDayLow": {"raw": 0.02765, "fmt": "0.0277"}, "regularMarketDayHigh": {"raw": 0.03, "fmt": "0.0300"}, "dividendRate": {}, "dividendYield": {}, "exDividendDate": {}, "payoutRatio": {"raw": 0.0, "fmt": "0.00%"}, "fiveYearAvgDividendYield": {}, "beta": {"raw": 3.506397, "fmt": "3.51"}, "forwardPE": {}, "volume": {"raw": 2472786, "fmt": "2.47M", "longFmt": "2,472,786"}, "regularMarketVolume": {"raw": 2472786, "fmt": "2.47M", "longFmt": "2,472,786"}, "averageVolume": {"raw": 3816138, "fmt": "3.82M", "longFmt": "3,816,138"}, "averageVolume10days": {"raw": 2938905, "fmt": "2.94M", "longFmt": "2,938,905"}, "averageDailyVolume10Day": {"raw": 2938905, "fmt": "2.94M", "longFmt": "2,938,905"}, "bid": {"raw": 0.0, "fmt": "0.0000"}, "ask": {"raw": 0.0, "fmt": "0.0000"}, "bidSize": {"raw": 0, "fmt": null, "longFmt": "0"}, "askSize": {"raw": 0, "fmt": null, "longFmt": "0"}, "marketCap": {"raw": 27253542, "fmt": "27.25M", "longFmt": "27,253,542"}, "yield": {}, "ytdReturn": {}, "totalAssets": {}, "expireDate": {}, "strikePrice": {}, "openInterest": {}, "fiftyTwoWeekLow": {"raw": 0.0262, "fmt": "0.0262"}, "fiftyTwoWeekHigh": {"raw": 0.118, "fmt": "0.1180"}, "priceToSalesTrailing12Months": {"raw": 137.64415, "fmt": "137.64"}, "fiftyDayAverage": {"raw": 0.038608, "fmt": "0.0386"}, "twoHundredDayAverage": {"raw": 0.05056325, "fmt": "0.0506"}, "trailingAnnualDividendRate": {}, "trailingAnnualDividendYield": {}, "navPrice": {}, "currency": "USD", "fromCurrency": null, "lastMarket": null, "volume24Hr": {}, "volumeAllCurrencies": {}, "circulatingSupply": {}, "algorithm": null, "maxSupply": {}, "startDate": {}, "tradeable": false}, "insiderHolders": {"holders": [{"maxAge": 1, "name": "DENN ROBERT ALLEN JR", "relation": "Director", "url": "", "transactionDescription": "Sale", "latestTransDate": {"raw": 1329264000, "fmt": "2012-02-15"}, "positionDirect": {"raw": 1015120, "fmt": "1.02M", "longFmt": "1,015,120"}, "positionDirectDate": {"raw": 1329264000, "fmt": "2012-02-15"}}, {"maxAge": 1, "name": "KAY MARK L", "relation": "Chief Executive Officer", "url": "", "transactionDescription": "Stock Award(Grant)", "latestTransDate": {"raw": 1513900800, "fmt": "2017-12-22"}, "positionDirectDate": {"raw": 1513900800, "fmt": "2017-12-22"}}, {"maxAge": 1, "name": "PEMMARAJU RAMARAO", "relation": "Chief Technology Officer", "url": "", "transactionDescription": "Stock Award(Grant)", "latestTransDate": {"raw": 1608163200, "fmt": "2020-12-17"}, "positionSummaryDate": {"raw": 1608163200, "fmt": "2020-12-17"}}, {"maxAge": 1, "name": "SOLAKIAN JAMES R", "relation": "Beneficial Owner of more than 10% of a Class of Security", "url": "", "transactionDescription": "Purchase", "latestTransDate": {"raw": 1253491200, "fmt": "2009-09-21"}, "positionDirect": {"raw": 3145500, "fmt": "3.15M", "longFmt": "3,145,500"}, "positionDirectDate": {"raw": 1253491200, "fmt": "2009-09-21"}}, {"maxAge": 1, "name": "WALLER GEORGE", "relation": "Officer and Director", "url": "", "transactionDescription": "Stock Award(Grant)", "latestTransDate": {"raw": 1608595200, "fmt": "2020-12-22"}, "positionSummaryDate": {"raw": 1608595200, "fmt": "2020-12-22"}}], "maxAge": 1}, "calendarEvents": {"maxAge": 1, "earnings": {"earningsDate": [{"raw": 1606089600, "fmt": "2020-11-23"}], "earningsAverage": {}, "earningsLow": {}, "earningsHigh": {}, "revenueAverage": {}, "revenueLow": {}, "revenueHigh": {}}, "exDividendDate": {}, "dividendDate": {"raw": 1593043200, "fmt": "2020-06-25"}}, "upgradeDowngradeHistory": {"history": [], "maxAge": 86400}, "price": {"maxAge": 1, "preMarketChange": {}, "preMarketPrice": {}, "postMarketChange": {}, "postMarketPrice": {}, "regularMarketChangePercent": {"raw": 0.023255808, "fmt": "2.33%"}, "regularMarketChange": {"raw": 0.0006499998, "fmt": "0.0006"}, "regularMarketTime": 1650657410, "priceHint": {"raw": 4, "fmt": "4", "longFmt": "4"}, "regularMarketPrice": {"raw": 0.0286, "fmt": "0.0286"}, "regularMarketDayHigh": {"raw": 0.03, "fmt": "0.0300"}, "regularMarketDayLow": {"raw": 0.02765, "fmt": "0.0277"}, "regularMarketVolume": {"raw": 2472786, "fmt": "2.47M", "longFmt": "2,472,786.00"}, "averageDailyVolume10Day": {"raw": 2938905, "fmt": "2.94M", "longFmt": "2,938,905"}, "averageDailyVolume3Month": {"raw": 3816138, "fmt": "3.82M", "longFmt": "3,816,138"}, "regularMarketPreviousClose": {"raw": 0.02826, "fmt": "0.0283"}, "regularMarketSource": "DELAYED", "regularMarketOpen": {"raw": 0.0279, "fmt": "0.0279"}, "strikePrice": {}, "openInterest": {}, "exchange": "PNK", "exchangeName": "Other OTC", "exchangeDataDelayedBy": 0, "marketState": "CLOSED", "quoteType": "EQUITY", "symbol": "SFOR", "underlyingSymbol": null, "shortName": "STRIKEFORCE TECHNOLOGIES INC", "longName": "StrikeForce Technologies, Inc.", "currency": "USD", "quoteSourceName": "Delayed Quote", "currencySymbol": "$", "fromCurrency": null, "lastMarket": null, "volume24Hr": {}, "volumeAllCurrencies": {}, "circulatingSupply": {}, "marketCap": {"raw": 27253542, "fmt": "27.25M", "longFmt": "27,253,542.00"}}, "balanceSheetHistory": {"balanceSheetStatements": [{"maxAge": 1, "endDate": {"raw": 1609372800, "fmt": "2020-12-31"}, "cash": {"raw": 162000, "fmt": "162k", "longFmt": "162,000"}, "netReceivables": {"raw": 20000, "fmt": "20k", "longFmt": "20,000"}, "totalCurrentAssets": {"raw": 203000, "fmt": "203k", "longFmt": "203,000"}, "propertyPlantEquipment": {"raw": 159000, "fmt": "159k", "longFmt": "159,000"}, "otherAssets": {"raw": 14000, "fmt": "14k", "longFmt": "14,000"}, "totalAssets": {"raw": 376000, "fmt": "376k", "longFmt": "376,000"}, "accountsPayable": {"raw": 1010000, "fmt": "1.01M", "longFmt": "1,010,000"}, "shortLongTermDebt": {"raw": 4969000, "fmt": "4.97M", "longFmt": "4,969,000"}, "otherCurrentLiab": {"raw": 1663000, "fmt": "1.66M", "longFmt": "1,663,000"}, "longTermDebt": {"raw": 463000, "fmt": "463k", "longFmt": "463,000"}, "minorityInterest": {"raw": -823000, "fmt": "-823k", "longFmt": "-823,000"}, "totalCurrentLiabilities": {"raw": 14130000, "fmt": "14.13M", "longFmt": "14,130,000"}, "totalLiab": {"raw": 14718000, "fmt": "14.72M", "longFmt": "14,718,000"}, "commonStock": {"raw": 72000, "fmt": "72k", "longFmt": "72,000"}, "retainedEarnings": {"raw": -54396000, "fmt": "-54.4M", "longFmt": "-54,396,000"}, "capitalSurplus": {"raw": 39814000, "fmt": "39.81M", "longFmt": "39,814,000"}, "totalStockholderEquity": {"raw": -14510000, "fmt": "-14.51M", "longFmt": "-14,510,000"}, "netTangibleAssets": {"raw": -14510000, "fmt": "-14.51M", "longFmt": "-14,510,000"}}, {"maxAge": 1, "endDate": {"raw": 1577750400, "fmt": "2019-12-31"}, "cash": {"raw": 75000, "fmt": "75k", "longFmt": "75,000"}, "netReceivables": {"raw": 20000, "fmt": "20k", "longFmt": "20,000"}, "totalCurrentAssets": {"raw": 99000, "fmt": "99k", "longFmt": "99,000"}, "propertyPlantEquipment": {"raw": 211000, "fmt": "211k", "longFmt": "211,000"}, "otherAssets": {"raw": 17000, "fmt": "17k", "longFmt": "17,000"}, "totalAssets": {"raw": 327000, "fmt": "327k", "longFmt": "327,000"}, "accountsPayable": {"raw": 1116000, "fmt": "1.12M", "longFmt": "1,116,000"}, "shortLongTermDebt": {"raw": 5197000, "fmt": "5.2M", "longFmt": "5,197,000"}, "otherCurrentLiab": {"raw": 3016000, "fmt": "3.02M", "longFmt": "3,016,000"}, "longTermDebt": {"raw": 148000, "fmt": "148k", "longFmt": "148,000"}, "minorityInterest": {"raw": -778000, "fmt": "-778k", "longFmt": "-778,000"}, "totalCurrentLiabilities": {"raw": 15481000, "fmt": "15.48M", "longFmt": "15,481,000"}, "totalLiab": {"raw": 15791000, "fmt": "15.79M", "longFmt": "15,791,000"}, "commonStock": {"raw": 1000, "fmt": "1k", "longFmt": "1,000"}, "retainedEarnings": {"raw": -44353000, "fmt": "-44.35M", "longFmt": "-44,353,000"}, "capitalSurplus": {"raw": 28675000, "fmt": "28.68M", "longFmt": "28,675,000"}, "totalStockholderEquity": {"raw": -15677000, "fmt": "-15.68M", "longFmt": "-15,677,000"}, "netTangibleAssets": {"raw": -15677000, "fmt": "-15.68M", "longFmt": "-15,677,000"}}, {"maxAge": 1, "endDate": {"raw": 1546214400, "fmt": "2018-12-31"}, "cash": {"raw": 86160, "fmt": "86.16k", "longFmt": "86,160"}, "netReceivables": {"raw": 20649, "fmt": "20.65k", "longFmt": "20,649"}, "totalCurrentAssets": {"raw": 111339, "fmt": "111.34k", "longFmt": "111,339"}, "propertyPlantEquipment": {"raw": 9259, "fmt": "9.26k", "longFmt": "9,259"}, "otherAssets": {"raw": 18430, "fmt": "18.43k", "longFmt": "18,430"}, "totalAssets": {"raw": 139028, "fmt": "139.03k", "longFmt": "139,028"}, "accountsPayable": {"raw": 945669, "fmt": "945.67k", "longFmt": "945,669"}, "shortLongTermDebt": {"raw": 4928020, "fmt": "4.93M", "longFmt": "4,928,020"}, "otherCurrentLiab": {"raw": 2813904, "fmt": "2.81M", "longFmt": "2,813,904"}, "minorityInterest": {"raw": -555740, "fmt": "-555.74k", "longFmt": "-555,740"}, "totalCurrentLiabilities": {"raw": 13941532, "fmt": "13.94M", "longFmt": "13,941,532"}, "totalLiab": {"raw": 13941532, "fmt": "13.94M", "longFmt": "13,941,532"}, "commonStock": {"raw": 237374, "fmt": "237.37k", "longFmt": "237,374"}, "retainedEarnings": {"raw": -40824610, "fmt": "-40.82M", "longFmt": "-40,824,610"}, "capitalSurplus": {"raw": 26349805, "fmt": "26.35M", "longFmt": "26,349,805"}, "totalStockholderEquity": {"raw": -14237431, "fmt": "-14.24M", "longFmt": "-14,237,431"}, "netTangibleAssets": {"raw": -14237431, "fmt": "-14.24M", "longFmt": "-14,237,431"}}, {"maxAge": 1, "endDate": {"raw": 1514678400, "fmt": "2017-12-31"}, "cash": {"raw": 455484, "fmt": "455.48k", "longFmt": "455,484"}, "netReceivables": {"raw": 47454, "fmt": "47.45k", "longFmt": "47,454"}, "totalCurrentAssets": {"raw": 512036, "fmt": "512.04k", "longFmt": "512,036"}, "propertyPlantEquipment": {"raw": 7676, "fmt": "7.68k", "longFmt": "7,676"}, "otherAssets": {"raw": 20485, "fmt": "20.48k", "longFmt": "20,485"}, "totalAssets": {"raw": 540197, "fmt": "540.2k", "longFmt": "540,197"}, "accountsPayable": {"raw": 957440, "fmt": "957.44k", "longFmt": "957,440"}, "shortLongTermDebt": {"raw": 4249937, "fmt": "4.25M", "longFmt": "4,249,937"}, "otherCurrentLiab": {"raw": 2123195, "fmt": "2.12M", "longFmt": "2,123,195"}, "totalCurrentLiabilities": {"raw": 11333383, "fmt": "11.33M", "longFmt": "11,333,383"}, "totalLiab": {"raw": 11333383, "fmt": "11.33M", "longFmt": "11,333,383"}, "commonStock": {"raw": 233584, "fmt": "233.58k", "longFmt": "233,584"}, "retainedEarnings": {"raw": -37543101, "fmt": "-37.54M", "longFmt": "-37,543,101"}, "capitalSurplus": {"raw": 25522331, "fmt": "25.52M", "longFmt": "25,522,331"}, "totalStockholderEquity": {"raw": -11787186, "fmt": "-11.79M", "longFmt": "-11,787,186"}, "netTangibleAssets": {"raw": -11787186, "fmt": "-11.79M", "longFmt": "-11,787,186"}}], "maxAge": 86400}, "earningsTrend": {"trend": [{"maxAge": 1, "period": "0q", "endDate": null, "growth": {}, "earningsEstimate": {"avg": {"raw": 0.0, "fmt": "0"}, "low": {"raw": 0.0, "fmt": "0"}, "high": {"raw": 0.0, "fmt": "0"}, "yearAgoEps": {}, "numberOfAnalysts": {"raw": 0, "fmt": null, "longFmt": "0"}, "growth": {}}, "revenueEstimate": {"avg": {"raw": 0, "fmt": null, "longFmt": "0"}, "low": {"raw": 0, "fmt": null, "longFmt": "0"}, "high": {"raw": 0, "fmt": null, "longFmt": "0"}, "numberOfAnalysts": {"raw": 0, "fmt": null, "longFmt": "0"}, "yearAgoRevenue": {}, "growth": {}}, "epsTrend": {"current": {"raw": 0.0, "fmt": "0"}, "7daysAgo": {"raw": 0.0, "fmt": "0"}, "30daysAgo": {"raw": 0.0, "fmt": "0"}, "60daysAgo": {"raw": 0.0, "fmt": "0"}, "90daysAgo": {"raw": 0.0, "fmt": "0"}}, "epsRevisions": {"upLast7days": {"raw": 0, "fmt": null, "longFmt": "0"}, "upLast30days": {"raw": 0, "fmt": null, "longFmt": "0"}, "downLast30days": {"raw": 0, "fmt": null, "longFmt": "0"}, "downLast90days": {}}}, {"maxAge": 1, "period": "+1q", "endDate": null, "growth": {}, "earningsEstimate": {"avg": {"raw": 0.0, "fmt": "0"}, "low": {"raw": 0.0, "fmt": "0"}, "high": {"raw": 0.0, "fmt": "0"}, "yearAgoEps": {}, "numberOfAnalysts": {"raw": 0, "fmt": null, "longFmt": "0"}, "growth": {}}, "revenueEstimate": {"avg": {"raw": 0, "fmt": null, "longFmt": "0"}, "low": {"raw": 0, "fmt": null, "longFmt": "0"}, "high": {"raw": 0, "fmt": null, "longFmt": "0"}, "numberOfAnalysts": {"raw": 0, "fmt": null, "longFmt": "0"}, "yearAgoRevenue": {}, "growth": {}}, "epsTrend": {"current": {"raw": 0.0, "fmt": "0"}, "7daysAgo": {"raw": 0.0, "fmt": "0"}, "30daysAgo": {"raw": 0.0, "fmt": "0"}, "60daysAgo": {"raw": 0.0, "fmt": "0"}, "90daysAgo": {"raw": 0.0, "fmt": "0"}}, "epsRevisions": {"upLast7days": {"raw": 0, "fmt": null, "longFmt": "0"}, "upLast30days": {"raw": 0, "fmt": null, "longFmt": "0"}, "downLast30days": {"raw": 0, "fmt": null, "longFmt": "0"}, "downLast90days": {}}}, {"maxAge": 1, "period": "0y", "endDate": null, "growth": {}, "earningsEstimate": {"avg": {"raw": 0.0, "fmt": "0"}, "low": {"raw": 0.0, "fmt": "0"}, "high": {"raw": 0.0, "fmt": "0"}, "yearAgoEps": {}, "numberOfAnalysts": {"raw": 0, "fmt": null, "longFmt": "0"}, "growth": {}}, "revenueEstimate": {"avg": {"raw": 0, "fmt": null, "longFmt": "0"}, "low": {"raw": 0, "fmt": null, "longFmt": "0"}, "high": {"raw": 0, "fmt": null, "longFmt": "0"}, "numberOfAnalysts": {"raw": 0, "fmt": null, "longFmt": "0"}, "yearAgoRevenue": {}, "growth": {}}, "epsTrend": {"current": {"raw": 0.0, "fmt": "0"}, "7daysAgo": {"raw": 0.0, "fmt": "0"}, "30daysAgo": {"raw": 0.0, "fmt": "0"}, "60daysAgo": {"raw": 0.0, "fmt": "0"}, "90daysAgo": {"raw": 0.0, "fmt": "0"}}, "epsRevisions": {"upLast7days": {"raw": 0, "fmt": null, "longFmt": "0"}, "upLast30days": {"raw": 0, "fmt": null, "longFmt": "0"}, "downLast30days": {"raw": 0, "fmt": null, "longFmt": "0"}, "downLast90days": {}}}, {"maxAge": 1, "period": "+1y", "endDate": null, "growth": {}, "earningsEstimate": {"avg": {"raw": 0.0, "fmt": "0"}, "low": {"raw": 0.0, "fmt": "0"}, "high": {"raw": 0.0, "fmt": "0"}, "yearAgoEps": {}, "numberOfAnalysts": {"raw": 0, "fmt": null, "longFmt": "0"}, "growth": {}}, "revenueEstimate": {"avg": {"raw": 0, "fmt": null, "longFmt": "0"}, "low": {"raw": 0, "fmt": null, "longFmt": "0"}, "high": {"raw": 0, "fmt": null, "longFmt": "0"}, "numberOfAnalysts": {"raw": 0, "fmt": null, "longFmt": "0"}, "yearAgoRevenue": {}, "growth": {}}, "epsTrend": {"current": {"raw": 0.0, "fmt": "0"}, "7daysAgo": {"raw": 0.0, "fmt": "0"}, "30daysAgo": {"raw": 0.0, "fmt": "0"}, "60daysAgo": {"raw": 0.0, "fmt": "0"}, "90daysAgo": {"raw": 0.0, "fmt": "0"}}, "epsRevisions": {"upLast7days": {"raw": 0, "fmt": null, "longFmt": "0"}, "upLast30days": {"raw": 0, "fmt": null, "longFmt": "0"}, "downLast30days": {"raw": 0, "fmt": null, "longFmt": "0"}, "downLast90days": {}}}, {"maxAge": 1, "period": "+5y", "endDate": null, "growth": {}, "earningsEstimate": {"avg": {}, "low": {}, "high": {}, "yearAgoEps": {}, "numberOfAnalysts": {}, "growth": {}}, "revenueEstimate": {"avg": {}, "low": {}, "high": {}, "numberOfAnalysts": {}, "yearAgoRevenue": {}, "growth": {}}, "epsTrend": {"current": {}, "7daysAgo": {}, "30daysAgo": {}, "60daysAgo": {}, "90daysAgo": {}}, "epsRevisions": {"upLast7days": {}, "upLast30days": {}, "downLast30days": {}, "downLast90days": {}}}, {"maxAge": 1, "period": "-5y", "endDate": null, "growth": {}, "earningsEstimate": {"avg": {}, "low": {}, "high": {}, "yearAgoEps": {}, "numberOfAnalysts": {}, "growth": {}}, "revenueEstimate": {"avg": {}, "low": {}, "high": {}, "numberOfAnalysts": {}, "yearAgoRevenue": {}, "growth": {}}, "epsTrend": {"current": {}, "7daysAgo": {}, "30daysAgo": {}, "60daysAgo": {}, "90daysAgo": {}}, "epsRevisions": {"upLast7days": {}, "upLast30days": {}, "downLast30days": {}, "downLast90days": {}}}], "maxAge": 1}, "secFilings": {"filings": [{"date": "2020-06-29", "epochDate": 1593388800, "type": "10-Q", "title": "Quarterly Report", "url": "http://biz.yahoo.com/e/200629/sfor10-q.html", "edgarUrl": "https://yahoo.brand.edgar-online.com/DisplayFiling.aspx?TabIndex=2&dcn=0001477932-20-003644&nav=1&src=Yahoo", "maxAge": 1}, {"date": "2020-06-25", "epochDate": 1593043200, "type": "8-K", "title": "Notice of Delisting or Failure to Satisfy a Continued Listing Rule", "url": "http://biz.yahoo.com/e/200625/sfor8-k.html", "edgarUrl": "https://yahoo.brand.edgar-online.com/DisplayFiling.aspx?TabIndex=2&dcn=0001477932-20-003537&nav=1&src=Yahoo", "maxAge": 1}, {"date": "2020-05-20", "epochDate": 1589932800, "type": "8-K", "title": "Other Events, Financial Statements and Exhibits", "url": "http://biz.yahoo.com/e/200520/sfor8-k.html", "edgarUrl": "https://yahoo.brand.edgar-online.com/DisplayFiling.aspx?TabIndex=2&dcn=0001477932-20-002961&nav=1&src=Yahoo", "maxAge": 1}, {"date": "2020-05-15", "epochDate": 1589500800, "type": "8-K", "title": "Other Events", "url": "http://biz.yahoo.com/e/200515/sfor8-k.html", "edgarUrl": "https://yahoo.brand.edgar-online.com/DisplayFiling.aspx?TabIndex=2&dcn=0001477932-20-002738&nav=1&src=Yahoo", "maxAge": 1}, {"date": "2020-05-01", "epochDate": 1588291200, "type": "10-K", "title": "Annual Report", "url": "http://biz.yahoo.com/e/200501/sfor10-k.html", "edgarUrl": "https://yahoo.brand.edgar-online.com/DisplayFiling.aspx?TabIndex=2&dcn=0001477932-20-002343&nav=1&src=Yahoo", "maxAge": 1}, {"date": "2020-03-31", "epochDate": 1585612800, "type": "8-K", "title": "Other Events", "url": "http://biz.yahoo.com/e/200331/sfor8-k.html", "edgarUrl": "https://yahoo.brand.edgar-online.com/DisplayFiling.aspx?TabIndex=2&dcn=0001477932-20-001741&nav=1&src=Yahoo", "maxAge": 1}, {"date": "2019-12-02", "epochDate": 1575244800, "type": "8-K", "title": "Submission of Matters to a Vote of Security Holders", "url": "http://biz.yahoo.com/e/191202/sfor8-k.html", "edgarUrl": "https://yahoo.brand.edgar-online.com/DisplayFiling.aspx?TabIndex=2&dcn=0001477932-19-006876&nav=1&src=Yahoo", "maxAge": 1}, {"date": "2019-11-18", "epochDate": 1574035200, "type": "10-Q", "title": "Quarterly Report", "url": "http://biz.yahoo.com/e/191118/sfor10-q.html", "edgarUrl": "https://yahoo.brand.edgar-online.com/DisplayFiling.aspx?TabIndex=2&dcn=0001477932-19-006657&nav=1&src=Yahoo", "maxAge": 1}, {"date": "2019-08-19", "epochDate": 1566172800, "type": "10-Q", "title": "Quarterly Report", "url": "http://biz.yahoo.com/e/190819/sfor10-q.html", "edgarUrl": "https://yahoo.brand.edgar-online.com/DisplayFiling.aspx?TabIndex=2&dcn=0001477932-19-004990&nav=1&src=Yahoo", "maxAge": 1}, {"date": "2019-07-16", "epochDate": 1563235200, "type": "8-K", "title": "Amendments to Articles of Inc. or Bylaws; Change in Fiscal Year, Fi", "url": "http://biz.yahoo.com/e/190716/sfor8-k.html", "edgarUrl": "https://yahoo.brand.edgar-online.com/DisplayFiling.aspx?TabIndex=2&dcn=0001477932-19-004129&nav=1&src=Yahoo", "maxAge": 1}], "maxAge": 86400}, "institutionOwnership": {"ownershipList": [], "maxAge": 1}, "majorHoldersBreakdown": {"maxAge": 1, "insidersPercentHeld": {"raw": 0.08632, "fmt": "8.63%"}, "institutionsPercentHeld": {"raw": 0.0, "fmt": "0.00%"}, "institutionsFloatPercentHeld": {"raw": 0.0, "fmt": "0.00%"}, "institutionsCount": {"raw": 0, "fmt": null, "longFmt": "0"}}, "balanceSheetHistoryQuarterly": {"balanceSheetStatements": [{"maxAge": 1, "endDate": {"raw": 1632960000, "fmt": "2021-09-30"}, "cash": {"raw": 3180000, "fmt": "3.18M", "longFmt": "3,180,000"}, "netReceivables": {"raw": 12000, "fmt": "12k", "longFmt": "12,000"}, "totalCurrentAssets": {"raw": 3203000, "fmt": "3.2M", "longFmt": "3,203,000"}, "propertyPlantEquipment": {"raw": 120000, "fmt": "120k", "longFmt": "120,000"}, "otherAssets": {"raw": 13000, "fmt": "13k", "longFmt": "13,000"}, "totalAssets": {"raw": 3336000, "fmt": "3.34M", "longFmt": "3,336,000"}, "accountsPayable": {"raw": 1029000, "fmt": "1.03M", "longFmt": "1,029,000"}, "shortLongTermDebt": {"raw": 4377000, "fmt": "4.38M", "longFmt": "4,377,000"}, "otherCurrentLiab": {"raw": 1500000, "fmt": "1.5M", "longFmt": "1,500,000"}, "longTermDebt": {"raw": 327000, "fmt": "327k", "longFmt": "327,000"}, "minorityInterest": {"raw": -860000, "fmt": "-860k", "longFmt": "-860,000"}, "totalCurrentLiabilities": {"raw": 13591000, "fmt": "13.59M", "longFmt": "13,591,000"}, "totalLiab": {"raw": 14004000, "fmt": "14M", "longFmt": "14,004,000"}, "commonStock": {"raw": 95000, "fmt": "95k", "longFmt": "95,000"}, "retainedEarnings": {"raw": -70201000, "fmt": "-70.2M", "longFmt": "-70,201,000"}, "capitalSurplus": {"raw": 59307000, "fmt": "59.31M", "longFmt": "59,307,000"}, "totalStockholderEquity": {"raw": -10799000, "fmt": "-10.8M", "longFmt": "-10,799,000"}, "netTangibleAssets": {"raw": -10799000, "fmt": "-10.8M", "longFmt": "-10,799,000"}}, {"maxAge": 1, "endDate": {"raw": 1625011200, "fmt": "2021-06-30"}, "cash": {"raw": 1348000, "fmt": "1.35M", "longFmt": "1,348,000"}, "netReceivables": {"raw": 11000, "fmt": "11k", "longFmt": "11,000"}, "totalCurrentAssets": {"raw": 1386000, "fmt": "1.39M", "longFmt": "1,386,000"}, "propertyPlantEquipment": {"raw": 133000, "fmt": "133k", "longFmt": "133,000"}, "otherAssets": {"raw": 13000, "fmt": "13k", "longFmt": "13,000"}, "totalAssets": {"raw": 1532000, "fmt": "1.53M", "longFmt": "1,532,000"}, "accountsPayable": {"raw": 1034000, "fmt": "1.03M", "longFmt": "1,034,000"}, "shortLongTermDebt": {"raw": 4403000, "fmt": "4.4M", "longFmt": "4,403,000"}, "otherCurrentLiab": {"raw": 1500000, "fmt": "1.5M", "longFmt": "1,500,000"}, "longTermDebt": {"raw": 327000, "fmt": "327k", "longFmt": "327,000"}, "minorityInterest": {"raw": -840000, "fmt": "-840k", "longFmt": "-840,000"}, "totalCurrentLiabilities": {"raw": 13534000, "fmt": "13.53M", "longFmt": "13,534,000"}, "totalLiab": {"raw": 13960000, "fmt": "13.96M", "longFmt": "13,960,000"}, "commonStock": {"raw": 88000, "fmt": "88k", "longFmt": "88,000"}, "retainedEarnings": {"raw": -69368000, "fmt": "-69.37M", "longFmt": "-69,368,000"}, "capitalSurplus": {"raw": 56701000, "fmt": "56.7M", "longFmt": "56,701,000"}, "totalStockholderEquity": {"raw": -12579000, "fmt": "-12.58M", "longFmt": "-12,579,000"}, "netTangibleAssets": {"raw": -12579000, "fmt": "-12.58M", "longFmt": "-12,579,000"}}, {"maxAge": 1, "endDate": {"raw": 1617148800, "fmt": "2021-03-31"}, "cash": {"raw": 816000, "fmt": "816k", "longFmt": "816,000"}, "netReceivables": {"raw": 17000, "fmt": "17k", "longFmt": "17,000"}, "totalCurrentAssets": {"raw": 856000, "fmt": "856k", "longFmt": "856,000"}, "propertyPlantEquipment": {"raw": 146000, "fmt": "146k", "longFmt": "146,000"}, "otherAssets": {"raw": 14000, "fmt": "14k", "longFmt": "14,000"}, "totalAssets": {"raw": 1016000, "fmt": "1.02M", "longFmt": "1,016,000"}, "accountsPayable": {"raw": 1002000, "fmt": "1M", "longFmt": "1,002,000"}, "shortLongTermDebt": {"raw": 4475000, "fmt": "4.47M", "longFmt": "4,475,000"}, "otherCurrentLiab": {"raw": 1500000, "fmt": "1.5M", "longFmt": "1,500,000"}, "longTermDebt": {"raw": 640000, "fmt": "640k", "longFmt": "640,000"}, "minorityInterest": {"raw": -830000, "fmt": "-830k", "longFmt": "-830,000"}, "totalCurrentLiabilities": {"raw": 13508000, "fmt": "13.51M", "longFmt": "13,508,000"}, "totalLiab": {"raw": 14247000, "fmt": "14.25M", "longFmt": "14,247,000"}, "commonStock": {"raw": 81000, "fmt": "81k", "longFmt": "81,000"}, "retainedEarnings": {"raw": -64335000, "fmt": "-64.33M", "longFmt": "-64,335,000"}, "capitalSurplus": {"raw": 50862000, "fmt": "50.86M", "longFmt": "50,862,000"}, "totalStockholderEquity": {"raw": -13392000, "fmt": "-13.39M", "longFmt": "-13,392,000"}, "netTangibleAssets": {"raw": -13392000, "fmt": "-13.39M", "longFmt": "-13,392,000"}}, {"maxAge": 1, "endDate": {"raw": 1609372800, "fmt": "2020-12-31"}, "cash": {"raw": 162000, "fmt": "162k", "longFmt": "162,000"}, "netReceivables": {"raw": 20000, "fmt": "20k", "longFmt": "20,000"}, "totalCurrentAssets": {"raw": 203000, "fmt": "203k", "longFmt": "203,000"}, "propertyPlantEquipment": {"raw": 159000, "fmt": "159k", "longFmt": "159,000"}, "otherAssets": {"raw": 14000, "fmt": "14k", "longFmt": "14,000"}, "totalAssets": {"raw": 376000, "fmt": "376k", "longFmt": "376,000"}, "accountsPayable": {"raw": 1010000, "fmt": "1.01M", "longFmt": "1,010,000"}, "shortLongTermDebt": {"raw": 4969000, "fmt": "4.97M", "longFmt": "4,969,000"}, "otherCurrentLiab": {"raw": 1663000, "fmt": "1.66M", "longFmt": "1,663,000"}, "longTermDebt": {"raw": 463000, "fmt": "463k", "longFmt": "463,000"}, "minorityInterest": {"raw": -823000, "fmt": "-823k", "longFmt": "-823,000"}, "totalCurrentLiabilities": {"raw": 14130000, "fmt": "14.13M", "longFmt": "14,130,000"}, "totalLiab": {"raw": 14718000, "fmt": "14.72M", "longFmt": "14,718,000"}, "commonStock": {"raw": 72000, "fmt": "72k", "longFmt": "72,000"}, "retainedEarnings": {"raw": -54396000, "fmt": "-54.4M", "longFmt": "-54,396,000"}, "capitalSurplus": {"raw": 39814000, "fmt": "39.81M", "longFmt": "39,814,000"}, "totalStockholderEquity": {"raw": -14510000, "fmt": "-14.51M", "longFmt": "-14,510,000"}, "netTangibleAssets": {"raw": -14510000, "fmt": "-14.51M", "longFmt": "-14,510,000"}}], "maxAge": 86400}, "earningsHistory": {"history": [{"maxAge": 1, "epsActual": {}, "epsEstimate": {}, "epsDifference": {}, "surprisePercent": {}, "quarter": {}, "period": "-4q"}, {"maxAge": 1, "epsActual": {}, "epsEstimate": {}, "epsDifference": {}, "surprisePercent": {}, "quarter": {}, "period": "-3q"}, {"maxAge": 1, "epsActual": {}, "epsEstimate": {}, "epsDifference": {}, "surprisePercent": {}, "quarter": {}, "period": "-2q"}, {"maxAge": 1, "epsActual": {}, "epsEstimate": {}, "epsDifference": {}, "surprisePercent": {}, "quarter": {}, "period": "-1q"}], "maxAge": 86400}, "majorDirectHolders": {"holders": [], "maxAge": 1}, "summaryProfile": {"address1": "1090 King Georges Post Road", "address2": "Suite 603", "city": "Edison", "state": "NJ", "zip": "08837", "country": "United States", "phone": "732 661 9641", "website": "https://www.strikeforcetech.com", "industry": "Software\u2014Infrastructure", "sector": "Technology", "longBusinessSummary": "StrikeForce Technologies, Inc. provides software development and services worldwide. The company develops and licenses various identification protection software products to protect computer networks from unauthorized access, as well as to protect network owners and users from cyber security attacks and data breaches. It offers ProtectID, an authentication platform to authenticate computer network users by various methods, including traditional passwords combined with a telephone, iPhone, Droid, Blackberry, PDA, multiple computer secure sessions, biometric identification, and encrypted devices, as well as through a push authentication method; and GuardedID that prevents the use of spyware/malware to collect user information. The company's products also comprise MobileTrust, an iPhone/iPad and Android device password vault that includes a password generator, as well as provides for mobile multi-factor one time password authentication; GuardedID mobile software development kit; SafeVchat video conferencing product; and PrivacyLok, which offers protective mechanisms. In addition, it provides software and hardware that are contractually licensed from other vendors, such as tokens, as well as additional authentication and telecommunication software devices. The company markets its products to financial service firms; healthcare related, legal services, virtual private network, technology service, and e-commerce companies; automotive; government agencies; multi-level marketing groups; and retail distributors, as well as the enterprise market in general. It sells its products directly to consumers through internet, distributors, resellers, third party agents, affiliates, and original equipment manufacturer agreements. The company was formerly known as StrikeForce Technical Services Corporation and changed its name to StrikeForce Technologies, Inc. in September 2004. StrikeForce Technologies, Inc. was incorporated in 2001 and is headquartered in Edison, New Jersey.", "fullTimeEmployees": 11, "companyOfficers": [], "maxAge": 86400}, "netSharePurchaseActivity": {"maxAge": 1, "period": "6m", "buyInfoCount": {"raw": 0, "fmt": null, "longFmt": "0"}, "buyInfoShares": {"raw": 0, "fmt": null, "longFmt": "0"}, "sellInfoCount": {"raw": 0, "fmt": null, "longFmt": "0"}, "netInfoCount": {"raw": 0, "fmt": null, "longFmt": "0"}, "netInfoShares": {"raw": 0, "fmt": null, "longFmt": "0"}, "netPercentInsiderShares": {"raw": 0.0, "fmt": "0.00%"}, "totalInsiderShares": {"raw": 82256120, "fmt": "82.26M", "longFmt": "82,256,120"}}, "insiderTransactions": {"transactions": [{"maxAge": 1, "shares": {"raw": 2272729, "fmt": "2.27M", "longFmt": "2,272,729"}, "value": {"raw": 5000, "fmt": "5k", "longFmt": "5,000"}, "filerUrl": "", "transactionText": "Stock Award(Grant) at price 0.00 per share.", "filerName": "WALLER GEORGE", "filerRelation": "Officer and Director", "moneyText": "", "startDate": {"raw": 1608595200, "fmt": "2020-12-22"}, "ownership": "D/I"}, {"maxAge": 1, "shares": {"raw": 9090909, "fmt": "9.09M", "longFmt": "9,090,909"}, "value": {"raw": 10000, "fmt": "10k", "longFmt": "10,000"}, "filerUrl": "", "transactionText": "Stock Award(Grant) at price 0.00 per share.", "filerName": "PEMMARAJU RAMARAO", "filerRelation": "Chief Technology Officer", "moneyText": "", "startDate": {"raw": 1608163200, "fmt": "2020-12-17"}, "ownership": "D/I"}, {"maxAge": 1, "shares": {"raw": 10000000, "fmt": "10M", "longFmt": "10,000,000"}, "filerUrl": "", "transactionText": "", "filerName": "KAY MARK L", "filerRelation": "Chief Executive Officer", "moneyText": "", "startDate": {"raw": 1513900800, "fmt": "2017-12-22"}, "ownership": "D"}, {"maxAge": 1, "shares": {"raw": 10000000, "fmt": "10M", "longFmt": "10,000,000"}, "filerUrl": "", "transactionText": "", "filerName": "PEMMARAJU RAMARAO", "filerRelation": "Director", "moneyText": "", "startDate": {"raw": 1513900800, "fmt": "2017-12-22"}, "ownership": "D"}, {"maxAge": 1, "shares": {"raw": 10000000, "fmt": "10M", "longFmt": "10,000,000"}, "filerUrl": "", "transactionText": "", "filerName": "WALLER GEORGE", "filerRelation": "Director", "moneyText": "", "startDate": {"raw": 1513900800, "fmt": "2017-12-22"}, "ownership": "D/I"}, {"maxAge": 1, "shares": {"raw": 228300, "fmt": "228.3k", "longFmt": "228,300"}, "value": {"raw": 3419, "fmt": "3.42k", "longFmt": "3,419"}, "filerUrl": "", "transactionText": "Sale at price 0.01 - 0.02 per share.", "filerName": "DENN ROBERT ALLEN JR", "filerRelation": "Director", "moneyText": "", "startDate": {"raw": 1329264000, "fmt": "2012-02-15"}, "ownership": "D"}, {"maxAge": 1, "shares": {"raw": 1498210, "fmt": "1.5M", "longFmt": "1,498,210"}, "value": {"raw": 29964, "fmt": "29.96k", "longFmt": "29,964"}, "filerUrl": "", "transactionText": "Purchase at price 0.02 per share.", "filerName": "DENN ROBERT ALLEN JR", "filerRelation": "Director", "moneyText": "", "startDate": {"raw": 1325808000, "fmt": "2012-01-06"}, "ownership": "D"}, {"maxAge": 1, "shares": {"raw": 100000, "fmt": "100k", "longFmt": "100,000"}, "value": {"raw": 2232, "fmt": "2.23k", "longFmt": "2,232"}, "filerUrl": "", "transactionText": "Purchase at price 0.01 - 0.03 per share.", "filerName": "DENN ROBERT ALLEN JR", "filerRelation": "Director", "moneyText": "", "startDate": {"raw": 1269475200, "fmt": "2010-03-25"}, "ownership": "D"}, {"maxAge": 1, "shares": {"raw": 250000, "fmt": "250k", "longFmt": "250,000"}, "value": {"raw": 24750, "fmt": "24.75k", "longFmt": "24,750"}, "filerUrl": "", "transactionText": "Purchase at price 0.10 per share.", "filerName": "SOLAKIAN JAMES R", "filerRelation": "Beneficial Owner of more than 10% of a Class of Security", "moneyText": "", "startDate": {"raw": 1253491200, "fmt": "2009-09-21"}, "ownership": "D"}, {"maxAge": 1, "shares": {"raw": 100000, "fmt": "100k", "longFmt": "100,000"}, "value": {"raw": 3000, "fmt": "3k", "longFmt": "3,000"}, "filerUrl": "", "transactionText": "Purchase at price 0.03 per share.", "filerName": "DENN ROBERT ALLEN JR", "filerRelation": "Director", "moneyText": "", "startDate": {"raw": 1251417600, "fmt": "2009-08-28"}, "ownership": "D"}, {"maxAge": 1, "shares": {"raw": 100000, "fmt": "100k", "longFmt": "100,000"}, "value": {"raw": 3012, "fmt": "3.01k", "longFmt": "3,012"}, "filerUrl": "", "transactionText": "Purchase at price 0.03 per share.", "filerName": "DENN ROBERT ALLEN JR", "filerRelation": "Director", "moneyText": "", "startDate": {"raw": 1251417600, "fmt": "2009-08-28"}, "ownership": "D"}, {"maxAge": 1, "shares": {"raw": 300001, "fmt": "300k", "longFmt": "300,001"}, "value": {"raw": 10200, "fmt": "10.2k", "longFmt": "10,200"}, "filerUrl": "", "transactionText": "Purchase at price 0.03 per share.", "filerName": "SOLAKIAN JAMES R", "filerRelation": "Beneficial Owner of more than 10% of a Class of Security", "moneyText": "", "startDate": {"raw": 1250640000, "fmt": "2009-08-19"}, "ownership": "D"}, {"maxAge": 1, "shares": {"raw": 99999, "fmt": "100k", "longFmt": "99,999"}, "value": {"raw": 3000, "fmt": "3k", "longFmt": "3,000"}, "filerUrl": "", "transactionText": "Purchase at price 0.03 per share.", "filerName": "SOLAKIAN JAMES R", "filerRelation": "Beneficial Owner of more than 10% of a Class of Security", "moneyText": "", "startDate": {"raw": 1245888000, "fmt": "2009-06-25"}, "ownership": "D"}, {"maxAge": 1, "shares": {"raw": 51000, "fmt": "51k", "longFmt": "51,000"}, "value": {"raw": 561, "fmt": "561", "longFmt": "561"}, "filerUrl": "", "transactionText": "Purchase at price 0.01 per share.", "filerName": "SOLAKIAN JAMES R", "filerRelation": "Beneficial Owner of more than 10% of a Class of Security", "moneyText": "", "startDate": {"raw": 1215388800, "fmt": "2008-07-07"}, "ownership": "D"}, {"maxAge": 1, "shares": {"raw": 51000, "fmt": "51k", "longFmt": "51,000"}, "value": {"raw": 561, "fmt": "561", "longFmt": "561"}, "filerUrl": "", "transactionText": "Purchase at price 0.01 per share.", "filerName": "SOLAKIAN JAMES R", "filerRelation": "Beneficial Owner of more than 10% of a Class of Security", "moneyText": "", "startDate": {"raw": 1215388800, "fmt": "2008-07-07"}, "ownership": "D"}, {"maxAge": 1, "shares": {"raw": 585500, "fmt": "585.5k", "longFmt": "585,500"}, "value": {"raw": 116755, "fmt": "116.75k", "longFmt": "116,755"}, "filerUrl": "", "transactionText": "Purchase at price 0.05 - 0.40 per share.", "filerName": "SOLAKIAN JAMES R", "filerRelation": "Beneficial Owner of more than 10% of a Class of Security", "moneyText": "", "startDate": {"raw": 1215388800, "fmt": "2008-07-07"}, "ownership": "D"}, {"maxAge": 1, "shares": {"raw": 144000, "fmt": "144k", "longFmt": "144,000"}, "value": {"raw": 1584, "fmt": "1.58k", "longFmt": "1,584"}, "filerUrl": "", "transactionText": "Purchase at price 0.01 per share.", "filerName": "SOLAKIAN JAMES R", "filerRelation": "Beneficial Owner of more than 10% of a Class of Security", "moneyText": "", "startDate": {"raw": 1215043200, "fmt": "2008-07-03"}, "ownership": "D"}, {"maxAge": 1, "shares": {"raw": 144000, "fmt": "144k", "longFmt": "144,000"}, "value": {"raw": 1584, "fmt": "1.58k", "longFmt": "1,584"}, "filerUrl": "", "transactionText": "Purchase at price 0.01 per share.", "filerName": "SOLAKIAN JAMES R", "filerRelation": "Beneficial Owner of more than 10% of a Class of Security", "moneyText": "", "startDate": {"raw": 1215043200, "fmt": "2008-07-03"}, "ownership": "D"}], "maxAge": 1}, "sectorTrend": {"maxAge": 1, "symbol": null, "peRatio": {}, "pegRatio": {}, "estimates": []}, "incomeStatementHistoryQuarterly": {"incomeStatementHistory": [{"maxAge": 1, "endDate": {"raw": 1632960000, "fmt": "2021-09-30"}, "totalRevenue": {"raw": 40000, "fmt": "40k", "longFmt": "40,000"}, "costOfRevenue": {"raw": 7000, "fmt": "7k", "longFmt": "7,000"}, "grossProfit": {"raw": 33000, "fmt": "33k", "longFmt": "33,000"}, "researchDevelopment": {"raw": 112000, "fmt": "112k", "longFmt": "112,000"}, "sellingGeneralAdministrative": {"raw": 672000, "fmt": "672k", "longFmt": "672,000"}, "nonRecurring": {}, "otherOperatingExpenses": {}, "totalOperatingExpenses": {"raw": 791000, "fmt": "791k", "longFmt": "791,000"}, "operatingIncome": {"raw": -751000, "fmt": "-751k", "longFmt": "-751,000"}, "totalOtherIncomeExpenseNet": {"raw": -102000, "fmt": "-102k", "longFmt": "-102,000"}, "ebit": {"raw": -751000, "fmt": "-751k", "longFmt": "-751,000"}, "interestExpense": {"raw": -102000, "fmt": "-102k", "longFmt": "-102,000"}, "incomeBeforeTax": {"raw": -853000, "fmt": "-853k", "longFmt": "-853,000"}, "incomeTaxExpense": {"raw": 0, "fmt": null, "longFmt": "0"}, "minorityInterest": {"raw": -860000, "fmt": "-860k", "longFmt": "-860,000"}, "netIncomeFromContinuingOps": {"raw": -853000, "fmt": "-853k", "longFmt": "-853,000"}, "discontinuedOperations": {}, "extraordinaryItems": {}, "effectOfAccountingCharges": {}, "otherItems": {}, "netIncome": {"raw": -833000, "fmt": "-833k", "longFmt": "-833,000"}, "netIncomeApplicableToCommonShares": {"raw": -833000, "fmt": "-833k", "longFmt": "-833,000"}}, {"maxAge": 1, "endDate": {"raw": 1625011200, "fmt": "2021-06-30"}, "totalRevenue": {"raw": 67000, "fmt": "67k", "longFmt": "67,000"}, "costOfRevenue": {"raw": 8000, "fmt": "8k", "longFmt": "8,000"}, "grossProfit": {"raw": 59000, "fmt": "59k", "longFmt": "59,000"}, "researchDevelopment": {"raw": 129000, "fmt": "129k", "longFmt": "129,000"}, "sellingGeneralAdministrative": {"raw": 1820000, "fmt": "1.82M", "longFmt": "1,820,000"}, "nonRecurring": {}, "otherOperatingExpenses": {}, "totalOperatingExpenses": {"raw": 1957000, "fmt": "1.96M", "longFmt": "1,957,000"}, "operatingIncome": {"raw": -1890000, "fmt": "-1.89M", "longFmt": "-1,890,000"}, "totalOtherIncomeExpenseNet": {"raw": -3153000, "fmt": "-3.15M", "longFmt": "-3,153,000"}, "ebit": {"raw": -1890000, "fmt": "-1.89M", "longFmt": "-1,890,000"}, "interestExpense": {"raw": -143000, "fmt": "-143k", "longFmt": "-143,000"}, "incomeBeforeTax": {"raw": -5043000, "fmt": "-5.04M", "longFmt": "-5,043,000"}, "incomeTaxExpense": {"raw": 0, "fmt": null, "longFmt": "0"}, "minorityInterest": {"raw": -840000, "fmt": "-840k", "longFmt": "-840,000"}, "netIncomeFromContinuingOps": {"raw": -5043000, "fmt": "-5.04M", "longFmt": "-5,043,000"}, "discontinuedOperations": {}, "extraordinaryItems": {}, "effectOfAccountingCharges": {}, "otherItems": {}, "netIncome": {"raw": -5033000, "fmt": "-5.03M", "longFmt": "-5,033,000"}, "netIncomeApplicableToCommonShares": {"raw": -5033000, "fmt": "-5.03M", "longFmt": "-5,033,000"}}, {"maxAge": 1, "endDate": {"raw": 1617148800, "fmt": "2021-03-31"}, "totalRevenue": {"raw": 46000, "fmt": "46k", "longFmt": "46,000"}, "costOfRevenue": {"raw": 3000, "fmt": "3k", "longFmt": "3,000"}, "grossProfit": {"raw": 43000, "fmt": "43k", "longFmt": "43,000"}, "researchDevelopment": {"raw": 145000, "fmt": "145k", "longFmt": "145,000"}, "sellingGeneralAdministrative": {"raw": 5628000, "fmt": "5.63M", "longFmt": "5,628,000"}, "nonRecurring": {}, "otherOperatingExpenses": {}, "totalOperatingExpenses": {"raw": 5776000, "fmt": "5.78M", "longFmt": "5,776,000"}, "operatingIncome": {"raw": -5730000, "fmt": "-5.73M", "longFmt": "-5,730,000"}, "totalOtherIncomeExpenseNet": {"raw": -4216000, "fmt": "-4.22M", "longFmt": "-4,216,000"}, "ebit": {"raw": -5730000, "fmt": "-5.73M", "longFmt": "-5,730,000"}, "interestExpense": {"raw": -151000, "fmt": "-151k", "longFmt": "-151,000"}, "incomeBeforeTax": {"raw": -9946000, "fmt": "-9.95M", "longFmt": "-9,946,000"}, "incomeTaxExpense": {"raw": 0, "fmt": null, "longFmt": "0"}, "minorityInterest": {"raw": -830000, "fmt": "-830k", "longFmt": "-830,000"}, "netIncomeFromContinuingOps": {"raw": -9946000, "fmt": "-9.95M", "longFmt": "-9,946,000"}, "discontinuedOperations": {}, "extraordinaryItems": {}, "effectOfAccountingCharges": {}, "otherItems": {}, "netIncome": {"raw": -9939000, "fmt": "-9.94M", "longFmt": "-9,939,000"}, "netIncomeApplicableToCommonShares": {"raw": -9939000, "fmt": "-9.94M", "longFmt": "-9,939,000"}}, {"maxAge": 1, "endDate": {"raw": 1609372800, "fmt": "2020-12-31"}, "totalRevenue": {"raw": 45311, "fmt": "45.31k", "longFmt": "45,311"}, "costOfRevenue": {"raw": 1749, "fmt": "1.75k", "longFmt": "1,749"}, "grossProfit": {"raw": 43562, "fmt": "43.56k", "longFmt": "43,562"}, "researchDevelopment": {"raw": 146846, "fmt": "146.85k", "longFmt": "146,846"}, "sellingGeneralAdministrative": {"raw": 872985, "fmt": "872.99k", "longFmt": "872,985"}, "nonRecurring": {}, "otherOperatingExpenses": {}, "totalOperatingExpenses": {"raw": 1021580, "fmt": "1.02M", "longFmt": "1,021,580"}, "operatingIncome": {"raw": -976269, "fmt": "-976.27k", "longFmt": "-976,269"}, "totalOtherIncomeExpenseNet": {"raw": -6169783, "fmt": "-6.17M", "longFmt": "-6,169,783"}, "ebit": {"raw": -976269, "fmt": "-976.27k", "longFmt": "-976,269"}, "interestExpense": {"raw": -162225, "fmt": "-162.22k", "longFmt": "-162,225"}, "incomeBeforeTax": {"raw": -7146052, "fmt": "-7.15M", "longFmt": "-7,146,052"}, "incomeTaxExpense": {"raw": 0, "fmt": null, "longFmt": "0"}, "minorityInterest": {"raw": -823000, "fmt": "-823k", "longFmt": "-823,000"}, "netIncomeFromContinuingOps": {"raw": -7146052, "fmt": "-7.15M", "longFmt": "-7,146,052"}, "discontinuedOperations": {}, "extraordinaryItems": {}, "effectOfAccountingCharges": {}, "otherItems": {}, "netIncome": {"raw": -7131135, "fmt": "-7.13M", "longFmt": "-7,131,135"}, "netIncomeApplicableToCommonShares": {"raw": -7131135, "fmt": "-7.13M", "longFmt": "-7,131,135"}}], "maxAge": 86400}, "cashflowStatementHistoryQuarterly": {"cashflowStatements": [{"maxAge": 1, "endDate": {"raw": 1632960000, "fmt": "2021-09-30"}, "netIncome": {"raw": -833000, "fmt": "-833k", "longFmt": "-833,000"}, "depreciation": {"raw": 14000, "fmt": "14k", "longFmt": "14,000"}, "changeToNetincome": {"raw": -8000, "fmt": "-8k", "longFmt": "-8,000"}, "changeToLiabilities": {"raw": 20000, "fmt": "20k", "longFmt": "20,000"}, "changeToOperatingActivities": {"raw": 64000, "fmt": "64k", "longFmt": "64,000"}, "totalCashFromOperatingActivities": {"raw": -743000, "fmt": "-743k", "longFmt": "-743,000"}, "netBorrowings": {"raw": -26000, "fmt": "-26k", "longFmt": "-26,000"}, "totalCashFromFinancingActivities": {"raw": 2575000, "fmt": "2.58M", "longFmt": "2,575,000"}, "changeInCash": {"raw": 1832000, "fmt": "1.83M", "longFmt": "1,832,000"}, "issuanceOfStock": {"raw": 2601000, "fmt": "2.6M", "longFmt": "2,601,000"}}, {"maxAge": 1, "endDate": {"raw": 1625011200, "fmt": "2021-06-30"}, "netIncome": {"raw": -5033000, "fmt": "-5.03M", "longFmt": "-5,033,000"}, "depreciation": {"raw": 15000, "fmt": "15k", "longFmt": "15,000"}, "changeToNetincome": {"raw": 4197000, "fmt": "4.2M", "longFmt": "4,197,000"}, "changeToAccountReceivables": {"raw": 5000, "fmt": "5k", "longFmt": "5,000"}, "changeToLiabilities": {"raw": 7000, "fmt": "7k", "longFmt": "7,000"}, "changeToOperatingActivities": {"raw": 94000, "fmt": "94k", "longFmt": "94,000"}, "totalCashFromOperatingActivities": {"raw": -686000, "fmt": "-686k", "longFmt": "-686,000"}, "netBorrowings": {"raw": -100000, "fmt": "-100k", "longFmt": "-100,000"}, "totalCashFromFinancingActivities": {"raw": 1218000, "fmt": "1.22M", "longFmt": "1,218,000"}, "changeInCash": {"raw": 532000, "fmt": "532k", "longFmt": "532,000"}, "issuanceOfStock": {"raw": 1318000, "fmt": "1.32M", "longFmt": "1,318,000"}}, {"maxAge": 1, "endDate": {"raw": 1617148800, "fmt": "2021-03-31"}, "netIncome": {"raw": -9939000, "fmt": "-9.94M", "longFmt": "-9,939,000"}, "depreciation": {"raw": 13000, "fmt": "13k", "longFmt": "13,000"}, "changeToNetincome": {"raw": 9304000, "fmt": "9.3M", "longFmt": "9,304,000"}, "changeToAccountReceivables": {"raw": 3000, "fmt": "3k", "longFmt": "3,000"}, "changeToLiabilities": {"raw": -8000, "fmt": "-8k", "longFmt": "-8,000"}, "changeToOperatingActivities": {"raw": 19000, "fmt": "19k", "longFmt": "19,000"}, "totalCashFromOperatingActivities": {"raw": -585000, "fmt": "-585k", "longFmt": "-585,000"}, "netBorrowings": {"raw": -210000, "fmt": "-210k", "longFmt": "-210,000"}, "totalCashFromFinancingActivities": {"raw": 1239000, "fmt": "1.24M", "longFmt": "1,239,000"}, "changeInCash": {"raw": 654000, "fmt": "654k", "longFmt": "654,000"}, "issuanceOfStock": {"raw": 1449000, "fmt": "1.45M", "longFmt": "1,449,000"}}, {"maxAge": 1, "endDate": {"raw": 1609372800, "fmt": "2020-12-31"}, "netIncome": {"raw": -7131135, "fmt": "-7.13M", "longFmt": "-7,131,135"}, "depreciation": {"raw": 14082, "fmt": "14.08k", "longFmt": "14,082"}, "changeToNetincome": {"raw": 6250772, "fmt": "6.25M", "longFmt": "6,250,772"}, "changeToAccountReceivables": {"raw": 2538, "fmt": "2.54k", "longFmt": "2,538"}, "changeToLiabilities": {"raw": -234613, "fmt": "-234.61k", "longFmt": "-234,613"}, "changeToOperatingActivities": {"raw": 152941, "fmt": "152.94k", "longFmt": "152,941"}, "totalCashFromOperatingActivities": {"raw": -927166, "fmt": "-927.17k", "longFmt": "-927,166"}, "capitalExpenditures": {"raw": 559, "fmt": "559", "longFmt": "559"}, "totalCashflowsFromInvestingActivities": {"raw": 559, "fmt": "559", "longFmt": "559"}, "netBorrowings": {"raw": 103868, "fmt": "103.87k", "longFmt": "103,868"}, "totalCashFromFinancingActivities": {"raw": 1079868, "fmt": "1.08M", "longFmt": "1,079,868"}, "changeInCash": {"raw": 153261, "fmt": "153.26k", "longFmt": "153,261"}, "issuanceOfStock": {"raw": 976000, "fmt": "976k", "longFmt": "976,000"}}], "maxAge": 86400}, "earnings": {"maxAge": 86400, "earningsChart": {"quarterly": [], "earningsDate": [{"raw": 1606089600, "fmt": "2020-11-23"}]}, "financialsChart": {"yearly": [{"date": 2017, "revenue": {"raw": 274137, "fmt": "274.14k", "longFmt": "274,137"}, "earnings": {"raw": -3206500, "fmt": "-3.21M", "longFmt": "-3,206,500"}}, {"date": 2018, "revenue": {"raw": 233878, "fmt": "233.88k", "longFmt": "233,878"}, "earnings": {"raw": -3281509, "fmt": "-3.28M", "longFmt": "-3,281,509"}}, {"date": 2019, "revenue": {"raw": 768000, "fmt": "768k", "longFmt": "768,000"}, "earnings": {"raw": -3528000, "fmt": "-3.53M", "longFmt": "-3,528,000"}}, {"date": 2020, "revenue": {"raw": 207000, "fmt": "207k", "longFmt": "207,000"}, "earnings": {"raw": -10043000, "fmt": "-10.04M", "longFmt": "-10,043,000"}}], "quarterly": [{"date": "4Q2020", "revenue": {"raw": 45311, "fmt": "45.31k", "longFmt": "45,311"}, "earnings": {"raw": -7131135, "fmt": "-7.13M", "longFmt": "-7,131,135"}}, {"date": "1Q2021", "revenue": {"raw": 46000, "fmt": "46k", "longFmt": "46,000"}, "earnings": {"raw": -9939000, "fmt": "-9.94M", "longFmt": "-9,939,000"}}, {"date": "2Q2021", "revenue": {"raw": 67000, "fmt": "67k", "longFmt": "67,000"}, "earnings": {"raw": -5033000, "fmt": "-5.03M", "longFmt": "-5,033,000"}}, {"date": "3Q2021", "revenue": {"raw": 40000, "fmt": "40k", "longFmt": "40,000"}, "earnings": {"raw": -833000, "fmt": "-833k", "longFmt": "-833,000"}}]}, "financialCurrency": "USD"}, "financialData": {"maxAge": 86400, "currentPrice": {"raw": 0.0286, "fmt": "0.03"}, "targetHighPrice": {}, "targetLowPrice": {}, "targetMeanPrice": {}, "targetMedianPrice": {}, "recommendationMean": {}, "recommendationKey": "none", "numberOfAnalystOpinions": {}, "totalCash": {"raw": 3180000, "fmt": "3.18M", "longFmt": "3,180,000"}, "totalCashPerShare": {"raw": 0.003, "fmt": "0"}, "ebitda": {"raw": -9343000, "fmt": "-9.34M", "longFmt": "-9,343,000"}, "totalDebt": {"raw": 6092000, "fmt": "6.09M", "longFmt": "6,092,000"}, "quickRatio": {"raw": 0.235, "fmt": "0.23"}, "currentRatio": {"raw": 0.236, "fmt": "0.24"}, "totalRevenue": {"raw": 198000, "fmt": "198k", "longFmt": "198,000"}, "debtToEquity": {}, "revenuePerShare": {"raw": 0.0, "fmt": "0.00"}, "returnOnAssets": {"raw": -3.2667599, "fmt": "-326.68%"}, "returnOnEquity": {}, "grossProfits": {"raw": 194000, "fmt": "194k", "longFmt": "194,000"}, "freeCashflow": {"raw": -71121, "fmt": "-71.12k", "longFmt": "-71,121"}, "operatingCashflow": {"raw": -2941000, "fmt": "-2.94M", "longFmt": "-2,941,000"}, "earningsGrowth": {}, "revenueGrowth": {"raw": -0.216, "fmt": "-21.60%"}, "grossMargins": {"raw": 0.89899004, "fmt": "89.90%"}, "ebitdaMargins": {"raw": 0.0, "fmt": "0.00%"}, "operatingMargins": {"raw": -47.21212, "fmt": "-4,721.21%"}, "profitMargins": {"raw": 0.0, "fmt": "0.00%"}, "financialCurrency": "USD"}}